ocx_reader/__init__.py
ocx_reader/loader/__init__.py
ocx_reader/loader/loader.py
ocx_reader/parser/__init__.py
ocx_reader/parser/parsers.py
ocx_reader/reader/__init__.py
ocx_reader/reader/reader.py
ocx_reader-0.1.0.dist-info/LICENSE
ocx_reader-0.1.0.dist-info/METADATA
ocx_reader-0.1.0.dist-info/WHEEL
ocx_reader-0.1.0.dist-info/RECORD
