Metadata-Version: 2.1
Name: ocx_reader
Version: 0.1.0
Summary: A python package reading OCX XML files with xsdata python bindings.
Author: Ole Chr. Astrup
Author-email: ole.christian.astrup@dnv.com
Requires-Python: >=3.10,<4.0
Classifier: Programming Language :: Python :: 3
Classifier: Programming Language :: Python :: 3.10
Classifier: Programming Language :: Python :: 3.11
Classifier: Programming Language :: Python :: 3.12
Requires-Dist: loguru
Requires-Dist: lxml
Requires-Dist: ocx
Requires-Dist: ocx_common
Requires-Dist: ocx_schema_parser
Requires-Dist: packaging (>=23.1,<24.0)
Requires-Dist: tbump
